Containerfile
HISTORY.md
LICENSE
MANIFEST.in
README.md
requirements.txt
setup.py
idupes/VERSION
idupes/__init__.py
idupes/__main__.py
idupes/base.py
idupes/cli.py
idupes.egg-info/PKG-INFO
idupes.egg-info/SOURCES.txt
idupes.egg-info/dependency_links.txt
idupes.egg-info/entry_points.txt
idupes.egg-info/requires.txt
idupes.egg-info/top_level.txt
idupes/__pycache__/__init__.cpython-38.pyc
idupes/__pycache__/__main__.cpython-38.pyc
idupes/__pycache__/cli.cpython-38.pyc
tests/.DS_Store
tests/__init__.py
tests/conftest.py
tests/example.txt
tests/test_base.py