Metadata-Version: 2.1
Name: idupes
Version: 0.0.5
Summary: Awesome idupes created by jimmysue
Home-page: https://github.com/jimmysue/idupes/
Author: jimmysue
License: UNKNOWN
Platform: UNKNOWN
